socialscan/__init__.py
socialscan/__main__.py
socialscan/cli.py
socialscan/platforms.py
socialscan/util.py
socialscan-2.0.1.dist-info/LICENSE
socialscan-2.0.1.dist-info/METADATA
socialscan-2.0.1.dist-info/WHEEL
socialscan-2.0.1.dist-info/entry_points.txt
socialscan-2.0.1.dist-info/top_level.txt
socialscan-2.0.1.dist-info/RECORD
