Metadata-Version: 2.1
Name: socialscan
Version: 2.0.1
Summary: Open-source intelligence tool for checking email address and username usage on online platforms
Home-page: https://github.com/iojw/socialscan
Author: Isaac Ong
Author-email: isaacong.jw@gmail.com
Keywords: email email-checker username username-checker social-media
Classifier: Development Status :: 4 - Beta
Classifier: Framework :: AsyncIO
Classifier: Environment :: Console
Classifier: Operating System :: OS Independent
Classifier: Topic :: Utilities
Classifier: License :: OSI Approved :: MIT License
Classifier: Programming Language :: Python :: 3.6
Classifier: Programming Language :: Python :: 3.7
Classifier: Programming Language :: Python :: 3.8
Requires-Python: >=3.6
Provides-Extra: tests
License-File: LICENSE
